MANIFEST.in
README.md
setup.py
bin/simmetrica-app.py
bin/simmetrica-cli.py
config/config.yml
src/simmetrica/__init__.py
src/simmetrica/simmetrica.py
src/simmetrica.egg-info/PKG-INFO
src/simmetrica.egg-info/SOURCES.txt
src/simmetrica.egg-info/dependency_links.txt
src/simmetrica.egg-info/not-zip-safe
src/simmetrica.egg-info/requires.txt
src/simmetrica.egg-info/top_level.txt
static/javascripts/app.js
static/javascripts/d3.min.js
static/javascripts/jquery-1.9.1.min.js
static/javascripts/jquery-ui-1.10.2.custom.min.js
static/javascripts/rickshaw.min.js
static/stylesheets/app.css
static/stylesheets/rickshaw.min.css
templates/index.html