Metadata-Version: 1.1
Name: simmetrica
Version: 1.0.1
Summary: Library for collecting, aggregating and visualizing event metrics as timeseries data
Home-page: https://github.com/o/simmetrica
Author: Osman Üngür
Author-email: osmanungur@gmail.com
License: MIT
Keywords: event,metric,timeseries,statistics
Platform: UNKNOWN
Classifier: Development Status :: 5 - Production/Stable
Classifier: Operating System :: OS Independent
Classifier: Programming Language :: Python :: 2
Classifier: Programming Language :: Python :: 2.6
Classifier: Programming Language :: Python :: 2.7
Classifier: Environment :: Console
Classifier: Intended Audience :: Developers
Classifier: Intended Audience :: End Users/Desktop
Classifier: Intended Audience :: System Administrators
Classifier: License :: OSI Approved :: MIT License
Classifier: Topic :: System :: Monitoring
